tamos/__init__.py
tamos/component.py
tamos/data_IO/__init__.py
tamos/data_IO/data_IO.py
tamos/element/__init__.py
tamos/element/element.py
tamos/elementIO/__init__.py
tamos/elementIO/elementIO_base.py
tamos/elementIO/element_cost.py
tamos/elementIO/grid.py
tamos/elementIO/load.py
tamos/hub.py
tamos/mask.py
tamos/network/HRE_thermal_network.py
tamos/network/__init__.py
tamos/network/network_base.py
tamos/network/non_thermal_network.py
tamos/network/thermal_network.py
tamos/optimization.py
tamos/production/Carto COP abs.png
tamos/production/__init__.py
tamos/production/boiler.py
tamos/production/cogeneration.py
tamos/production/dry_cooler.py
tamos/production/heat_exchanger.py
tamos/production/heat_pump.py
tamos/production/misc.py
tamos/production/production_base.py
tamos/production/solar.py
tamos/solve_tools/__init__.py
tamos/solve_tools/solve_tools.py
tamos/storage/__init__.py
tamos/storage/same_vector.py
tamos/storage/storage_base.py
tamos/storage/thermocline.py
tamos-0.1.0.dist-info/LICENSE
tamos-0.1.0.dist-info/WHEEL
tamos-0.1.0.dist-info/METADATA
tamos-0.1.0.dist-info/RECORD
