Metadata-Version: 2.1
Name: tamos
Version: 0.1.0
Summary: Thermal Architectures Modelling and Optimization Software
License: Apache-2.0
Author: BNerot
Requires-Python: >=3.7,<4.0
Classifier: License :: OSI Approved :: Apache Software License
Classifier: Programming Language :: Python :: 3
Classifier: Programming Language :: Python :: 3.7
Classifier: Programming Language :: Python :: 3.8
Classifier: Programming Language :: Python :: 3.9
Classifier: Programming Language :: Python :: 3.10
Classifier: Programming Language :: Python :: 3.11
Requires-Dist: docplex (>=2.24.0)
Requires-Dist: matplotlib (>3.0.0)
Requires-Dist: networkx (>=2.8)
Requires-Dist: numpy (>=1.0.0)
Requires-Dist: pandas (>=1)
Requires-Dist: scipy
Requires-Dist: sympy
